flask_api_resource
